lastfmgenre/__init__.py
lastfmgenre/genres-tree.yaml
lastfmgenre/genres.txt
lastfmgenre-0.1.2.dist-info/LICENSE
lastfmgenre-0.1.2.dist-info/METADATA
lastfmgenre-0.1.2.dist-info/WHEEL
lastfmgenre-0.1.2.dist-info/top_level.txt
lastfmgenre-0.1.2.dist-info/RECORD
