Metadata-Version: 2.1
Name: lastfmgenre
Version: 0.1.2
Summary: A module for getting sane genre results from Last.fm tags. Based on the lastgenre plugin for the Beets music library manager.
Author-email: mjvotaw <mjvotaw@gmail.com>
License: The MIT License
Project-URL: Homepage, https://github.com/mjvotaw/lastfmgenre
Project-URL: Bug Tracker, https://github.com/mjvotaw/lastfmgenre/issues
Classifier: Programming Language :: Python :: 3
Classifier: License :: OSI Approved :: MIT License
Classifier: Operating System :: OS Independent
Requires-Python: >=3.8
License-File: LICENSE
Requires-Dist: pyyaml
Requires-Dist: pylast
